datacpp/__init__.py
datacpp/dataloader.py
datacpp/libdatacpp.so
datacpp/pipeline.py
datacpp/test_box.py
datacpp-0.9.dist-info/METADATA
datacpp-0.9.dist-info/WHEEL
datacpp-0.9.dist-info/top_level.txt
datacpp-0.9.dist-info/RECORD
